{"version":1,"resource":"vscode-userdata:/home/ninh/.config/VSCodium/User/settings.json","entries":[{"id":"dv44.json","timestamp":1706356420144},{"id":"6jMi.json","timestamp":1706356455578},{"id":"I2Om.json","timestamp":1706356478734},{"id":"CCUz.json","timestamp":1706356524011},{"id":"VejP.json","timestamp":1706357766617},{"id":"shyE.json","timestamp":1706360450632},{"id":"iFXL.json","timestamp":1706362843643},{"id":"lJCz.json","timestamp":1706368129268},{"id":"Y4jJ.json","timestamp":1707850439565},{"id":"LvbZ.json","timestamp":1707850462855},{"id":"lVJN.json","timestamp":1707851789097},{"id":"9yFk.json","timestamp":1707854828024}]}